sa_csgo/__init__.py
sa_csgo/addons/gui.py
sa_csgo/config/config.json
sa_csgo/main.py
sa_csgo/procedures/access_csgo_server_console.py
sa_csgo/procedures/enable_realtime_kernel.py
sa_csgo/procedures/install_csgo_server.py
sa_csgo/procedures/install_sasm.py
sa_csgo/procedures/install_steamcmd.py
sa_csgo/procedures/start_csgo_server.py
sa_csgo/procedures/stop_csgo_server.py
sa_csgo/utils/config.py
sa_csgo/utils/format.py
sa_csgo/utils/os_commands.py
sa_csgo-1.0.3.dist-info/METADATA
sa_csgo-1.0.3.dist-info/WHEEL
sa_csgo-1.0.3.dist-info/entry_points.txt
sa_csgo-1.0.3.dist-info/RECORD
